swpwrxblock_build_backend/__init__.py
swpwrxblock_build_backend/backend.py
swpwrxblock_build_backend/collect_reactapp.py
swpwrxblock_build_backend/const.py
swpwrxblock_build_backend/utils.py
swpwrxblock_build_backend-18.0.5.dist-info/LICENSE.TXT
swpwrxblock_build_backend-18.0.5.dist-info/METADATA
swpwrxblock_build_backend-18.0.5.dist-info/WHEEL
swpwrxblock_build_backend-18.0.5.dist-info/top_level.txt
swpwrxblock_build_backend-18.0.5.dist-info/RECORD
