Metadata-Version: 2.1
Name: swpwrxblock-build-backend
Version: 18.0.5
Summary: Stepwise Power XBlock Build Backend
License: MIT
License-File: LICENSE.TXT
Requires-Dist: XBlock
Requires-Dist: requests
